pyemailer.py
pyemailer-1.0.9.dist-info/METADATA
pyemailer-1.0.9.dist-info/WHEEL
pyemailer-1.0.9.dist-info/top_level.txt
pyemailer-1.0.9.dist-info/RECORD
