Metadata-Version: 2.1
Name: pyemailer
Version: 1.0.9
Summary: A very simple, generic, python emailer that can send plain text emails or tornado template driven emails. 
Home-page: UNKNOWN
Author: Eric Rosenzweig
Author-email: rosenzweigit@gmail.com
License: UNKNOWN
Keywords: email,template
Platform: UNKNOWN
Requires: tornado
